planning_poker_jira/__init__.py
planning_poker_jira/admin.py
planning_poker_jira/apps.py
planning_poker_jira/forms.py
planning_poker_jira/models.py
planning_poker_jira/utils.py
planning_poker_jira/version.py
planning_poker_jira/locale/de/LC_MESSAGES/django.mo
planning_poker_jira/locale/de/LC_MESSAGES/django.po
planning_poker_jira/locale/en/LC_MESSAGES/django.mo
planning_poker_jira/locale/en/LC_MESSAGES/django.po
planning_poker_jira/migrations/0001_initial.py
planning_poker_jira/migrations/__init__.py
planning_poker_jira/templates/admin/planning_poker/story/export_story_points.html
planning_poker_jira/templates/admin/planning_poker_jira/jira_connection/import_stories.html
planning_poker_jira-1.0.0.dist-info/AUTHORS.rst
planning_poker_jira-1.0.0.dist-info/LICENSE
planning_poker_jira-1.0.0.dist-info/METADATA
planning_poker_jira-1.0.0.dist-info/WHEEL
planning_poker_jira-1.0.0.dist-info/top_level.txt
planning_poker_jira-1.0.0.dist-info/RECORD
