Metadata-Version: 2.1
Name: planning-poker-jira
Version: 1.0.0
Summary: A jira extension for the planning poker app
Home-page: https://github.com/rheinwerk-verlag/planning-poker-jira
Author: Rheinwerk Webteam
Author-email: webteam@rheinwerk-verlag.de
Maintainer: Rheinwerk Verlag GmbH Webteam
Maintainer-email: webteam@rheinwerk-verlag.de
License: BSD-3-Clause
Platform: UNKNOWN
Classifier: Development Status :: 5 - Production/Stable
Classifier: Environment :: Web Environment
Classifier: Framework :: Django
Classifier: Framework :: Django :: 3.0
Classifier: Framework :: Django :: 3.1
Classifier: Framework :: Django :: 3.2
Classifier: Intended Audience :: Developers
Classifier: Intended Audience :: End Users/Desktop
Classifier: License :: OSI Approved :: BSD License
Classifier: Operating System :: OS Independent
Classifier: Programming Language :: Python
Classifier: Programming Language :: Python :: 3.6
Classifier: Programming Language :: Python :: 3.7
Classifier: Programming Language :: Python :: 3.8
Classifier: Programming Language :: Python :: 3.9
Classifier: Topic :: Internet
License-File: LICENSE
License-File: AUTHORS.rst
Requires-Dist: django-searchable-encrypted-fields
Requires-Dist: jira (>=2.0.0)
Requires-Dist: planning-poker
